fklearn/__init__.py
fklearn/common_docstrings.py
fklearn/version.py
fklearn/causal/__init__.py
fklearn/causal/debias.py
fklearn/causal/effects.py
fklearn/causal/cate_learning/__init__.py
fklearn/causal/cate_learning/double_machine_learning.py
fklearn/causal/cate_learning/meta_learners.py
fklearn/causal/validation/__init__.py
fklearn/causal/validation/auc.py
fklearn/causal/validation/cate.py
fklearn/causal/validation/curves.py
fklearn/data/__init__.py
fklearn/data/datasets.py
fklearn/exceptions/__init__.py
fklearn/exceptions/exceptions.py
fklearn/metrics/__init__.py
fklearn/metrics/pd_extractors.py
fklearn/preprocessing/__init__.py
fklearn/preprocessing/rebalancing.py
fklearn/preprocessing/schema.py
fklearn/preprocessing/splitting.py
fklearn/resources/VERSION
fklearn/training/__init__.py
fklearn/training/calibration.py
fklearn/training/classification.py
fklearn/training/ensemble.py
fklearn/training/imputation.py
fklearn/training/pipeline.py
fklearn/training/regression.py
fklearn/training/transformation.py
fklearn/training/unsupervised.py
fklearn/training/utils.py
fklearn/tuning/__init__.py
fklearn/tuning/model_agnostic_fc.py
fklearn/tuning/parameter_tuners.py
fklearn/tuning/samplers.py
fklearn/tuning/selectors.py
fklearn/tuning/stoppers.py
fklearn/tuning/utils.py
fklearn/types/__init__.py
fklearn/types/types.py
fklearn/validation/__init__.py
fklearn/validation/evaluators.py
fklearn/validation/perturbators.py
fklearn/validation/splitters.py
fklearn/validation/validator.py
fklearn-4.0.1.dist-info/LICENSE
fklearn-4.0.1.dist-info/METADATA
fklearn-4.0.1.dist-info/WHEEL
fklearn-4.0.1.dist-info/top_level.txt
fklearn-4.0.1.dist-info/RECORD
