Metadata-Version: 2.2
Name: fklearn
Version: 4.0.1
Summary: Functional machine learning
Home-page: https://github.com/nubank/fklearn
Author: Nubank
Classifier: Programming Language :: Python :: 3.8
Classifier: Programming Language :: Python :: 3.9
Classifier: Programming Language :: Python :: 3.10
Classifier: Programming Language :: Python :: 3.11
Requires-Python: >=3.8,<3.12
License-File: LICENSE
Requires-Dist: joblib<2,>=1.3.2
Requires-Dist: numpy<2,>=1.24.4
Requires-Dist: pandas<3,>=2
Requires-Dist: scikit-learn<2,>=1
Requires-Dist: statsmodels<1,>=0.14.0
Requires-Dist: toolz<1,>=0.12.0
Provides-Extra: test-deps
Requires-Dist: pytest<8,>=7.4.3; extra == "test-deps"
Requires-Dist: pytest-cov<3,>=2.6.1; extra == "test-deps"
Requires-Dist: pytest-xdist<4,>=3.3.1; extra == "test-deps"
Requires-Dist: mypy<2,>=1.6.1; extra == "test-deps"
Requires-Dist: coverage<5; extra == "test-deps"
Requires-Dist: codecov<3,>=2.0; extra == "test-deps"
Requires-Dist: hypothesis<7,>=6.88.3; extra == "test-deps"
Provides-Extra: lgbm
Requires-Dist: lightgbm<4.6,>=4; extra == "lgbm"
Provides-Extra: xgboost
Requires-Dist: xgboost<3,>=2; extra == "xgboost"
Provides-Extra: catboost
Requires-Dist: catboost<2,>=1.2.2; extra == "catboost"
Provides-Extra: tools
Requires-Dist: shap<0.45,>=0.43; extra == "tools"
Requires-Dist: swifter<2,>=0.24; extra == "tools"
Provides-Extra: devel
Requires-Dist: pytest<8,>=7.4.3; extra == "devel"
Requires-Dist: pytest-cov<3,>=2.6.1; extra == "devel"
Requires-Dist: pytest-xdist<4,>=3.3.1; extra == "devel"
Requires-Dist: mypy<2,>=1.6.1; extra == "devel"
Requires-Dist: coverage<5; extra == "devel"
Requires-Dist: codecov<3,>=2.0; extra == "devel"
Requires-Dist: hypothesis<7,>=6.88.3; extra == "devel"
Requires-Dist: lightgbm<4.6,>=4; extra == "devel"
Requires-Dist: xgboost<3,>=2; extra == "devel"
Requires-Dist: catboost<2,>=1.2.2; extra == "devel"
Requires-Dist: shap<0.45,>=0.43; extra == "devel"
Requires-Dist: swifter<2,>=0.24; extra == "devel"
Provides-Extra: all-models
Requires-Dist: lightgbm<4.6,>=4; extra == "all-models"
Requires-Dist: xgboost<3,>=2; extra == "all-models"
Requires-Dist: catboost<2,>=1.2.2; extra == "all-models"
Provides-Extra: all
Requires-Dist: lightgbm<4.6,>=4; extra == "all"
Requires-Dist: xgboost<3,>=2; extra == "all"
Requires-Dist: catboost<2,>=1.2.2; extra == "all"
Requires-Dist: shap<0.45,>=0.43; extra == "all"
Requires-Dist: swifter<2,>=0.24; extra == "all"
Dynamic: author
Dynamic: classifier
Dynamic: description
Dynamic: description-content-type
Dynamic: home-page
Dynamic: provides-extra
Dynamic: requires-dist
Dynamic: requires-python
Dynamic: summary
